luckypost/__init__.py
luckypost/__main__.py
luckypost/luckypost.py
luckypost/luckypost_test.py
luckypost-0.9.3.dist-info/LICENSE
luckypost-0.9.3.dist-info/METADATA
luckypost-0.9.3.dist-info/WHEEL
luckypost-0.9.3.dist-info/top_level.txt
luckypost-0.9.3.dist-info/RECORD
