Metadata-Version: 2.1
Name: luckypost
Version: 0.9.3
Summary: Create and verify luckyposts
Home-page: https://github.com/mcilrain/luckypost
Author: Noah McIlraith
Author-email: noah.mcilraith@gmail.com
License: UNKNOWN
Project-URL: Bug Tracker, https://github.com/mcilrain/luckypost/issues
Platform: UNKNOWN
Classifier: Programming Language :: Python :: 3
Classifier: License :: OSI Approved :: MIT License
Classifier: Operating System :: OS Independent
Requires-Python: >=3.6
License-File: LICENSE
Requires-Dist: base58
Requires-Dist: ecdsa
Requires-Dist: pynacl
